.DS_Store
sgt/__init__.py
sgt/sgt.py
sgt/sgt_spark.py
sgt/SGT/SGT.py
sgt/SGT/__init__.py
sgt/sgt_spark/__init__.py
sgt/sgt_spark/sgt_spark.py
sgt-2.0.3.dist-info/LICENSE
sgt-2.0.3.dist-info/METADATA
sgt-2.0.3.dist-info/WHEEL
sgt-2.0.3.dist-info/top_level.txt
sgt-2.0.3.dist-info/RECORD
