Metadata-Version: 2.1
Name: sgt
Version: 2.0.3
Summary: Sequence Graph Transform (SGT) is a sequence embedding function. SGT extracts the short- and long-term sequence features and embeds them in a finite-dimensional feature space. The long and short term patterns embedded in SGT can be tuned without any increase in the computation.
Home-page: https://github.com/cran2367/sgt
Author: Chitta Ranjan
Author-email: cran2367@gmail.com
License: UNKNOWN
Platform: UNKNOWN
Classifier: Programming Language :: Python :: 3
Classifier: License :: OSI Approved :: MIT License
Classifier: Operating System :: OS Independent
